check_hashtag.py
Check_Hashtag-1.0.5.dist-info/LICENSE
Check_Hashtag-1.0.5.dist-info/METADATA
Check_Hashtag-1.0.5.dist-info/WHEEL
Check_Hashtag-1.0.5.dist-info/top_level.txt
Check_Hashtag-1.0.5.dist-info/RECORD
